tests/__init__.py
tests/test_cli.py
typesnatch/__init__.py
typesnatch/cli.py
typesnatch/core.py
typesnatch/utils.py
typesnatch-0.1.3.dist-info/LICENSE
typesnatch-0.1.3.dist-info/METADATA
typesnatch-0.1.3.dist-info/WHEEL
typesnatch-0.1.3.dist-info/entry_points.txt
typesnatch-0.1.3.dist-info/top_level.txt
typesnatch-0.1.3.dist-info/RECORD
