Metadata-Version: 2.2
Name: typesnatch
Version: 0.1.3
Summary: TypeSnatch: Install fonts the easy way
Home-page: https://github.com/brandon-fryslie/typesnatch
Author: Brandon Fryslie
Author-email: admin@swank.town
Classifier: Programming Language :: Python :: 3
Classifier: License :: OSI Approved :: MIT License
Classifier: Operating System :: OS Independent
Requires-Python: >=3.6
License-File: LICENSE
Requires-Dist: beautifulsoup4
Requires-Dist: click
Requires-Dist: colorama
Requires-Dist: playwright
Requires-Dist: requests
Requires-Dist: inquirer
Dynamic: author
Dynamic: author-email
Dynamic: classifier
Dynamic: description
Dynamic: description-content-type
Dynamic: home-page
Dynamic: requires-dist
Dynamic: requires-python
Dynamic: summary
